{
  "FreeLaHuflit": [
    {
      "name": "Hải Lê",
      "phone": "0346252626",
      "age": "23",
      "id": "cj9lM8oBg"
    },
    {
      "name": "Bán Vé Máy Bay",
      "phone": "0347637598",
      "age": "33",
      "id": "7ClWdzTPZ"
    },
    {
      "name": "thanh",
      "phone": "312312",
      "age": "23",
      "id": "38lVOeUCZ"
    },
    {
      "name": "Linh",
      "phone": "321321312312",
      "age": "23",
      "id": "fAwWA1DPk"
    },
    {
      "name": "Trang",
      "phone": "321312",
      "age": "323",
      "id": "8LzcvR__1"
    },
    {
      "name": "Phuong",
      "phone": "213",
      "age": "23",
      "id": "EM4wQDsKT"
    },
    {
      "name": "Lê Khắc Hải",
      "phone": "0346252626",
      "age": "23",
      "id": "AGrM-J7ve"
    },
    {
      "name": "Lê Khắc Hải11",
      "phone": "0346252626",
      "age": "33",
      "id": "P4WzykKZn"
    },
    {
      "name": "Lê Khắc Hải",
      "phone": "312312",
      "age": "23",
      "id": "mK5ud_jfL"
    },
    {
      "name": "duong",
      "phone": "123",
      "age": "22",
      "id": "ZSUILoi6X"
    },
    {
      "name": "hai",
      "phone": "0346252626",
      "age": "23",
      "id": "ctB9xsTHp"
    },
    {
      "name": "hihi",
      "phone": "0346252626",
      "age": "23",
      "id": "LD2ggbx_p"
    }
  ],
  "ListAccout": [
    {
      "id": "GreOBc7QX",
      "username": "lekhachai9999@gmail.com",
      "password": "4297f44b13955235245b2497399d7a93"
    },
    {
      "id": "6qCvY-gYH",
      "username": "haile",
      "password": "202cb962ac59075b964b07152d234b70"
    }
  ]
}